geojson2fromto/__init__.py
geojson2fromto/__main__.py
geojson2fromto/library/__init__.py
geojson2fromto/library/geojson2fromto.py
geojson2fromto-0.3.0.dist-info/entry_points.txt
geojson2fromto-0.3.0.dist-info/LICENSE
geojson2fromto-0.3.0.dist-info/WHEEL
geojson2fromto-0.3.0.dist-info/METADATA
geojson2fromto-0.3.0.dist-info/RECORD
