Metadata-Version: 2.1
Name: geojson2fromto
Version: 0.3.0
Summary: Python module to convert GeoJSON to the 'from-to' format used by deck.gl's LineLayer
Home-page: https://github.com/weaselandfox/geojson2fromto
License: UNKNOWN
Author: Weasel & Fox
Author-email: hello@weaselandfox.com
Classifier: License :: OSI Approved :: MIT License
Classifier: Programming Language :: Python :: 3.6
Requires-Dist: geopandas
Requires-Dist: simplejson
